dltoolbox/__init__.py
dltoolbox/aa_code.py
dltoolbox/functions.py
dltoolbox-0.0.4.dist-info/METADATA
dltoolbox-0.0.4.dist-info/WHEEL
dltoolbox-0.0.4.dist-info/licenses/LICENSE
dltoolbox-0.0.4.dist-info/RECORD
