Metadata-Version: 2.1
Name: dltoolbox
Version: 0.0.4
Summary: The Ding Lab Tool Box
Project-URL: Homepage, https://github.com/DingGroup/DLToolBox
Project-URL: Bug Tracker, https://github.com/DingGroup/DLToolBox/issues
Author-email: Xinqiang Ding <Xinqiang.Ding@tufts.edu>
License: MIT License
License-File: LICENSE
Classifier: License :: OSI Approved :: MIT License
Classifier: Operating System :: OS Independent
Classifier: Programming Language :: Python :: 3
Requires-Python: >=3.11
